html_msg/__init__.py
html_msg/html_message.py
html_msg/html_table.py
html_msg-1.0.7.dist-info/LICENSE.txt
html_msg-1.0.7.dist-info/METADATA
html_msg-1.0.7.dist-info/WHEEL
html_msg-1.0.7.dist-info/top_level.txt
html_msg-1.0.7.dist-info/RECORD
