Metadata-Version: 2.1
Name: html-msg
Version: 1.0.7
Summary: This tool allows you to create HTML messages using simple methods, without the need to write HTML code manually.
Home-page: https://github.com/Sirakan-B/html_msg/
Download-URL: https://pypi.org/project/html-msg/
Author: Sirakan Bagdasarian
Author-email: bsirak@bk.ru
License: MIT
Keywords: HTML,Message
License-File: LICENSE.txt
Requires-Dist: IPython
Requires-Dist: pandas
